tool_server_client/__about__.py
tool_server_client/__init__.py
tool_server_client/client.py
tool_server_client/examples.py
tool_server_client/main.py
tool_server_client/models.py
tool_server_client-0.0.1.dist-info/METADATA
tool_server_client-0.0.1.dist-info/WHEEL
tool_server_client-0.0.1.dist-info/licenses/LICENSE
tool_server_client-0.0.1.dist-info/RECORD
