Metadata-Version: 2.4
Name: tool-server-client
Version: 0.0.1
Summary: This is the Python SDK for Computer Use Tool Server, allowing you to easily control the computer desktop environment from your applications.
Project-URL: Documentation, https://github.com/lvlv/tool-server-client#readme
Project-URL: Issues, https://github.com/lvlv/tool-server-client/issues
Project-URL: Source, https://github.com/lvlv/tool-server-client
Author-email: lvlv <lvgj1998@gmail.com>
License-Expression: MIT
License-File: LICENSE
Classifier: Development Status :: 4 - Beta
Classifier: Programming Language :: Python
Classifier: Programming Language :: Python :: 3.8
Classifier: Programming Language :: Python :: 3.9
Classifier: Programming Language :: Python :: 3.10
Classifier: Programming Language :: Python :: 3.11
Classifier: Programming Language :: Python :: 3.12
Classifier: Programming Language :: Python :: Implementation :: CPython
Classifier: Programming Language :: Python :: Implementation :: PyPy
Requires-Python: >=3.8
Requires-Dist: pydantic>=1.8.0
Requires-Dist: requests>=2.25.0
